samplerate2.cpython-37m-darwin.so
samplerate2-0.0.2.dist-info/LICENSE
samplerate2-0.0.2.dist-info/METADATA
samplerate2-0.0.2.dist-info/WHEEL
samplerate2-0.0.2.dist-info/top_level.txt
samplerate2-0.0.2.dist-info/RECORD
