Metadata-Version: 2.1
Name: samplerate2
Version: 0.0.2
Summary: Monolithic python wrapper for libsamplerate
Home-page: https://github.com/fakufaku/python-samplerate2
Author: Robin Scheibler
Author-email: fakufaku@gmail.com
License-File: LICENSE
Requires-Dist: numpy
